pyarithmeticlib/.DS_Store
pyarithmeticlib/__init__.py
pyarithmeticlib/expression.py
pyarithmeticlib/generator.py
pyarithmeticlib-0.1.0.dist-info/LICENSE
pyarithmeticlib-0.1.0.dist-info/METADATA
pyarithmeticlib-0.1.0.dist-info/WHEEL
pyarithmeticlib-0.1.0.dist-info/RECORD
