Metadata-Version: 2.1
Name: pyarithmeticlib
Version: 0.1.0
Summary: A package to generate arithmetic expression
License: MIT
Author: amaurylekens
Requires-Python: >=3.9,<4.0
Classifier: License :: OSI Approved :: MIT License
Classifier: Programming Language :: Python :: 3
Classifier: Programming Language :: Python :: 3.9
Classifier: Programming Language :: Python :: 3.10
Classifier: Programming Language :: Python :: 3.11
Classifier: Programming Language :: Python :: 3.12
